.gitignore
.pre-commit-config.yaml
.yarnrc
MANIFEST.in
README.md
requirements.txt
setup.py
.ci/tag.sh
.github/workflows/github-actions.yml
sphinx_zama_theme/__init__.py
sphinx_zama_theme/bootstrap_html_translator.py
sphinx_zama_theme/docs-navbar.html
sphinx_zama_theme/docs-sidebar.html
sphinx_zama_theme/footer.html
sphinx_zama_theme/icon-links.html
sphinx_zama_theme/layout.html
sphinx_zama_theme/search-field.html
sphinx_zama_theme/theme.conf
sphinx_zama_theme.egg-info/PKG-INFO
sphinx_zama_theme.egg-info/SOURCES.txt
sphinx_zama_theme.egg-info/dependency_links.txt
sphinx_zama_theme.egg-info/entry_points.txt
sphinx_zama_theme.egg-info/requires.txt
sphinx_zama_theme.egg-info/top_level.txt
sphinx_zama_theme/_templates/copyright.html
sphinx_zama_theme/_templates/edit-this-page.html
sphinx_zama_theme/_templates/last-updated.html
sphinx_zama_theme/_templates/navbar-icon-links.html
sphinx_zama_theme/_templates/navbar-logo.html
sphinx_zama_theme/_templates/navbar-nav.html
sphinx_zama_theme/_templates/page-toc.html
sphinx_zama_theme/_templates/prev-next.html
sphinx_zama_theme/_templates/sidebar-ethical-ads.html
sphinx_zama_theme/_templates/sidebar-nav-bs.html
sphinx_zama_theme/_templates/sphinx-version.html
sphinx_zama_theme/static/favicon.ico
sphinx_zama_theme/static/logo.png
sphinx_zama_theme/static/webpack-macros.html
sphinx_zama_theme/static/zama-black.png
sphinx_zama_theme/static/zama-white.png
sphinx_zama_theme/static/css/blank.css
sphinx_zama_theme/static/css/index.38f2ebe09480739b4ba0fa585d02b29a.css
sphinx_zama_theme/static/css/theme.css
sphinx_zama_theme/static/js/index.30d17a8aef5d942e5d26.js
sphinx_zama_theme/static/js/version.js
sphinx_zama_theme/static/vendor/fontawesome/5.13.0/LICENSE.txt
sphinx_zama_theme/static/vendor/fontawesome/5.13.0/css/all.min.css
sphinx_zama_theme/static/vendor/fontawesome/5.13.0/webfonts/fa-brands-400.eot
sphinx_zama_theme/static/vendor/fontawesome/5.13.0/webfonts/fa-brands-400.svg
sphinx_zama_theme/static/vendor/fontawesome/5.13.0/webfonts/fa-brands-400.ttf
sphinx_zama_theme/static/vendor/fontawesome/5.13.0/webfonts/fa-brands-400.woff
sphinx_zama_theme/static/vendor/fontawesome/5.13.0/webfonts/fa-brands-400.woff2
