Metadata-Version: 2.1
Name: sphinx-zama-theme
Version: 3.0.3
Summary: Zama sphinx theme forked from PyData sphinx theme
Home-page: https://github.com/zama-ai/sphinx_zama_theme
Maintainer: Zama
Maintainer-email: hello@zama.ai
License: BSD
Platform: UNKNOWN
Classifier: Development Status :: 4 - Beta
Classifier: Programming Language :: Python :: 3
Classifier: Framework :: Sphinx
Classifier: Framework :: Sphinx :: Theme
Classifier: License :: OSI Approved :: BSD License
Classifier: Operating System :: OS Independent
Requires-Python: >=3.5
